{
  "generator-jhipster": {
    "applicationType": "monolith",
    "authenticationType": "jwt",
    "baseName": "ca3s",
    "blueprints": [],
    "buildTool": "maven",
    "cacheProvider": "ehcache",
    "clientFramework": "vue",
    "clientPackageManager": "npm",
    "clientTheme": "none",
    "clientThemeVariant": "",
    "creationTimestamp": 1578670205962,
    "databaseType": "sql",
    "devDatabaseType": "h2Disk",
    "devServerPort": 9060,
    "dtoSuffix": "DTO",
    "embeddableLaunchScript": false,
    "enableGradleEnterprise": false,
    "enableHibernateCache": false,
    "enableSwaggerCodegen": false,
    "enableTranslation": true,
    "entitySuffix": "",
    "jhiPrefix": "jhi",
    "jhipsterVersion": "7.9.3",
    "jwtSecretKey": "NDkyZWMyYTljNmZiOGQwMWFlMDUyM2ViYmIyNGFlNDEyMzE4NTM0MTA0NjhjMTFkNWViMmYzODRkNzEwNWZmMzQwN2MyNDA4N2UzNzZmZDEzYjVkZjIzYmY3Njg2NDVjZThkZGQyMzA4NTYyYjk0YzRmZGU4NmQwMWM2MDM3MWE=",
    "languages": ["en", "de", "pl"],
    "messageBroker": false,
    "microfrontend": false,
    "microfrontends": [],
    "nativeLanguage": "en",
    "otherModules": [],
    "packageFolder": "de/trustable/ca3s/core",
    "packageName": "de.trustable.ca3s.core",
    "pages": [],
    "prodDatabaseType": "mysql",
    "promptValues": {
      "nativeLanguage": "de",
      "packageName": "de.trustable.ca3s.core"
    },
    "reactive": false,
    "searchEngine": false,
    "serverPort": "8080",
    "serverSideOptions": [],
    "serviceDiscoveryType": false,
    "skipCheckLengthOfIdentifier": false,
    "skipClient": false,
    "skipFakeData": false,
    "skipUserManagement": false,
    "testFrameworks": [],
    "useSass": true,
    "websocket": "spring-websocket",
    "withAdminUi": true
  }
}
